setup.py
openxshareble/__init__.py
openxshareble/app.py
openxshareble.egg-info/PKG-INFO
openxshareble.egg-info/SOURCES.txt
openxshareble.egg-info/dependency_links.txt
openxshareble.egg-info/top_level.txt
openxshareble/ble/__init__.py
openxshareble/ble/attrs.py
openxshareble/ble/readdata.py
openxshareble/ble/uart.py