Metadata-Version: 1.0
Name: openxshareble
Version: 0.0.0
Summary: Python library for interacting with Dexcom G4 with Share over Bluetooth low energy.
Home-page: https://github.com/bewest/openxshareble/
Author: Ben West
Author-email: bewest@gmail.com
License: MIT
Platform: UNKNOWN
